wsd/__init__.py
wsd-0.0.1rc0.dist-info/licenses/LICENSE
wsd-0.0.1rc0.dist-info/METADATA
wsd-0.0.1rc0.dist-info/WHEEL
wsd-0.0.1rc0.dist-info/top_level.txt
wsd-0.0.1rc0.dist-info/RECORD
