Metadata-Version: 2.4
Name: wsd
Version: 0.0.1rc0
Summary: Multi-lingual Word Sense Disambiguation.
Author-email: Arnaud Rachez <arnaud@linalgo.com>, Farid Taba <farid.t@gmail.com>, Jack Dryvers <j.dryvers@proton.me>, Jean Cadic <me@cadic.jp>
License: MIT
Project-URL: Homepage, https://github.com/linalgo/wsd
Project-URL: Issues, https://github.com/linalgo/wsd/issues
Classifier: Programming Language :: Python :: 3
Classifier: License :: OSI Approved :: MIT License
Classifier: Operating System :: OS Independent
Requires-Python: >=3.10
License-File: LICENSE
Requires-Dist: fugashi[unidic]
Requires-Dist: google-cloud-bigquery
Requires-Dist: linalgo
Requires-Dist: mesop
Requires-Dist: numpy
Requires-Dist: pillow
Requires-Dist: rich
Requires-Dist: typer
Provides-Extra: dev
Requires-Dist: pytest; extra == "dev"
Requires-Dist: pre-commit; extra == "dev"
Dynamic: license-file
